CssAnimation101/README.md
CssAnimation101/__init__.py
CssAnimation101/__main__.py
CssAnimation101/file.epub
CssAnimation101/index.html
CssAnimation101/css/__init__.py
CssAnimation101/css/annotations.css
CssAnimation101/css/main.css
CssAnimation101/css/normalize.css
CssAnimation101/css/popup.css
CssAnimation101/font/__init__.py
CssAnimation101/font/fontello.eot
CssAnimation101/font/fontello.svg
CssAnimation101/font/fontello.ttf
CssAnimation101/font/fontello.woff
CssAnimation101/img/__init__.py
CssAnimation101/img/annotator-glyph-sprite.png
CssAnimation101/img/annotator-icon-sprite.png
CssAnimation101/img/apple-touch-icon.png
CssAnimation101/img/cancelfullscreen.png
CssAnimation101/img/close.png
CssAnimation101/img/fullscreen.png
CssAnimation101/img/loader.gif
CssAnimation101/img/menu-icon.png
CssAnimation101/img/save.png
CssAnimation101/img/saved.png
CssAnimation101/img/settings-s.png
CssAnimation101/img/settings.png
CssAnimation101/img/star.png
CssAnimation101/js/__init__.py
CssAnimation101/js/epub.js
CssAnimation101/js/epub.min.js
CssAnimation101/js/epub.min.map
CssAnimation101/js/hooks.min.js
CssAnimation101/js/hooks.min.map
CssAnimation101/js/reader.js
CssAnimation101/js/reader.js.map
CssAnimation101/js/reader.min.js
CssAnimation101/js/reader.min.map
CssAnimation101/js/hooks/__init__.py
CssAnimation101/js/hooks/extensions/__init__.py
CssAnimation101/js/hooks/extensions/highlight.js
CssAnimation101/js/libs/__init__.py
CssAnimation101/js/libs/jquery.min.js
CssAnimation101/js/libs/localforage.min.js
CssAnimation101/js/libs/screenfull.js
CssAnimation101/js/libs/screenfull.min.js
CssAnimation101/js/libs/zip.min.js
CssAnimation101/js/plugins/__init__.py
CssAnimation101/js/plugins/hypothesis.js
CssAnimation101/js/plugins/search.js
css_animation_101-2024.3.3.0.dist-info/METADATA
css_animation_101-2024.3.3.0.dist-info/WHEEL
css_animation_101-2024.3.3.0.dist-info/entry_points.txt
css_animation_101-2024.3.3.0.dist-info/top_level.txt
css_animation_101-2024.3.3.0.dist-info/RECORD
